GaugeRnR/__init__.py
GaugeRnR/__main__.py
GaugeRnR/application.py
GaugeRnR/dataLoader.py
GaugeRnR/gaugeRnR.py
GaugeRnR/generator.py
GaugeRnR/linearity.py
GaugeRnR/normality.py
GaugeRnR/reportGenerator.py
GaugeRnR/statistics.py
GaugeRnR/resources/__init__.py
GaugeRnR/resources/bootstrap.min.css
GaugeRnR/tests/__init__.py
GaugeRnR/tests/data.py
GaugeRnR/tests/test_application.py
GaugeRnR/tests/test_dataLoader.py
GaugeRnR/tests/test_gaugeRnR.py
GaugeRnR/tests/test_generator.py
GaugeRnR/tests/test_linearity.py
GaugeRnR/tests/test_normality.py
GaugeRnR/tests/test_statistics.py
GaugeRnR-0.6.0.dist-info/LICENSE
GaugeRnR-0.6.0.dist-info/METADATA
GaugeRnR-0.6.0.dist-info/WHEEL
GaugeRnR-0.6.0.dist-info/entry_points.txt
GaugeRnR-0.6.0.dist-info/top_level.txt
GaugeRnR-0.6.0.dist-info/RECORD
