Metadata-Version: 2.1
Name: GaugeRnR
Version: 0.6.0
Summary: A simple library for calculating Gauge RnR
Home-page: UNKNOWN
Author: Alexander Poole
Author-email: alex.o.poole@gmail.com
License: MIT
Project-URL: Source Code, https://github.com/owodunni/GaugeRnR
Keywords: statistics gagueR&R gageRnR anova gage gauge repetition repeatability R&R rnr
Platform: UNKNOWN
Classifier: Development Status :: 5 - Production/Stable
Classifier: Topic :: Scientific/Engineering :: Mathematics
Classifier: Intended Audience :: Developers
Classifier: License :: OSI Approved :: MIT License
Classifier: Operating System :: OS Independent
Classifier: Programming Language :: Python :: 3.5
Classifier: Programming Language :: Python :: 3.6
Classifier: Programming Language :: Python :: 3.7
Classifier: Programming Language :: Python :: 3.8
